MANIFEST.in
README.rst
setup.py
exam/__init__.py
exam/asserts.py
exam/cases.py
exam/decorators.py
exam/fixtures.py
exam/helpers.py
exam/mock.py
exam/objects.py
exam.egg-info/PKG-INFO
exam.egg-info/SOURCES.txt
exam.egg-info/dependency_links.txt
exam.egg-info/not-zip-safe
exam.egg-info/requires.txt
exam.egg-info/top_level.txt
tests/__init__.py
tests/dummy.py
tests/test_asserts.py
tests/test_cases.py
tests/test_decorators.py
tests/test_exam.py
tests/test_helpers.py
tests/test_mock.py
tests/test_objects.py