Metadata-Version: 1.1
Name: exam
Version: 0.10.6
Summary: Helpers for better testing.
Home-page: https://github.com/fluxx/exam
Author: Jeff Pollard
Author-email: jeff.pollard@gmail.com
License: MIT
Platform: UNKNOWN
Classifier: Programming Language :: Python
Classifier: Programming Language :: Python :: 2
Classifier: Programming Language :: Python :: 2.6
Classifier: Programming Language :: Python :: 2.7
Classifier: Programming Language :: Python :: 3
Classifier: Programming Language :: Python :: 3.2
Classifier: Programming Language :: Python :: 3.3
